finetuning/__init__.py
finetuning/finetuning_example.py
finetuning/finetuning_torch.py
timesfm/__init__.py
timesfm/data_loader.py
timesfm/patched_decoder.py
timesfm/pytorch_patched_decoder.py
timesfm/time_features.py
timesfm/timesfm_base.py
timesfm/timesfm_jax.py
timesfm/timesfm_torch.py
timesfm/xreg_lib.py
timesfm-1.3.0.dist-info/LICENSE
timesfm-1.3.0.dist-info/METADATA
timesfm-1.3.0.dist-info/WHEEL
timesfm-1.3.0.dist-info/RECORD
