Metadata-Version: 2.3
Name: timesfm
Version: 1.3.0
Summary: Open weights time-series foundation model from Google Research.
Keywords: time series,timesfm,forecast,time series model
Author: Rajat Sen
Author-email: senrajat@google.com
Requires-Python: >=3.10,<3.12
Classifier: Environment :: Console
Classifier: Framework :: Flake8
Classifier: Operating System :: OS Independent
Classifier: Programming Language :: Python :: 3
Classifier: Programming Language :: Python :: 3.10
Classifier: Programming Language :: Python :: 3.11
Classifier: Topic :: Software Development :: Documentation
Classifier: Topic :: Software Development :: Libraries :: Python Modules
Classifier: Topic :: Software Development :: Quality Assurance
Provides-Extra: pax
Provides-Extra: torch
Requires-Dist: absl-py (>=1.4.0)
Requires-Dist: einshape (>=1.0.0)
Requires-Dist: huggingface_hub[cli] (>=0.23.0)
Requires-Dist: jax[cuda12] (>=0.4.26) ; (python_version >= "3.10" and python_version < "3.12") and (extra == "pax")
Requires-Dist: jaxlib (>=0.4.26) ; (python_version >= "3.10" and python_version < "3.12") and (extra == "pax")
Requires-Dist: lingvo (>=0.12.7) ; (python_version == "3.10") and (extra == "pax")
Requires-Dist: numpy (>=1.26.4)
Requires-Dist: pandas (>=2.0.0)
Requires-Dist: paxml (>=1.4.0) ; (python_version == "3.10") and (extra == "pax")
Requires-Dist: scikit-learn (>=1.2.2)
Requires-Dist: torch[cuda] (>=2.0.0) ; (python_version == "3.11") and (extra == "torch")
Requires-Dist: typer (>=0.12.3)
Requires-Dist: utilsforecast (>=0.1.10)
Requires-Dist: wandb (>=0.17.5)
Project-URL: Homepage, https://github.com/google-research/timesfm
Project-URL: Repository, https://github.com/google-research/timesfm
